LICENSE
MANIFEST.in
README.md
setup.py
apimaticcalculatorpythonv7Demo/__init__.py
apimaticcalculatorpythonv7Demo/api_helper.py
apimaticcalculatorpythonv7Demo/apimaticcalculatorpythonv7_demo_client.py
apimaticcalculatorpythonv7Demo/configuration.py
apimaticcalculatorpythonv7Demo/decorators.py
apimaticcalculatorpythonv7Demo.egg-info/PKG-INFO
apimaticcalculatorpythonv7Demo.egg-info/SOURCES.txt
apimaticcalculatorpythonv7Demo.egg-info/dependency_links.txt
apimaticcalculatorpythonv7Demo.egg-info/requires.txt
apimaticcalculatorpythonv7Demo.egg-info/top_level.txt
apimaticcalculatorpythonv7Demo/controllers/__init__.py
apimaticcalculatorpythonv7Demo/controllers/base_controller.py
apimaticcalculatorpythonv7Demo/controllers/calculator_dev_ops_conf.py
apimaticcalculatorpythonv7Demo/exceptions/__init__.py
apimaticcalculatorpythonv7Demo/exceptions/api_exception.py
apimaticcalculatorpythonv7Demo/http/__init__.py
apimaticcalculatorpythonv7Demo/http/http_call_back.py
apimaticcalculatorpythonv7Demo/http/http_client.py
apimaticcalculatorpythonv7Demo/http/http_context.py
apimaticcalculatorpythonv7Demo/http/http_method_enum.py
apimaticcalculatorpythonv7Demo/http/http_request.py
apimaticcalculatorpythonv7Demo/http/http_response.py
apimaticcalculatorpythonv7Demo/http/requests_client.py
apimaticcalculatorpythonv7Demo/models/__init__.py
apimaticcalculatorpythonv7Demo/models/operation_type.py
tests/__init__.py
tests/http_response_catcher.py
tests/test_helper.py
tests/controllers/__init__.py
tests/controllers/controller_test_base.py
tests/controllers/test_calculator_dev_ops_conf.py